tyme/__init__.py
tyme/cli/__init__.py
tyme/cli/cli.py
tyme/cli/render.py
tyme/common.py
tyme/timeline.py
tyme/utils.py
tyme-0.1.5.dist-info/entry_points.txt
tyme-0.1.5.dist-info/WHEEL
tyme-0.1.5.dist-info/METADATA
tyme-0.1.5.dist-info/RECORD
