Metadata-Version: 2.1
Name: tyme
Version: 0.1.5
Summary: track your moments everywhere
Author: Enrico Borba
Author-email: enricozb@gmail.com
Requires-Python: >=3.7,<4.0
Classifier: Programming Language :: Python :: 3
Classifier: Programming Language :: Python :: 3.7
Requires-Dist: colorama (>=0.4.1,<0.5.0)
Requires-Dist: hjson (>=3.0,<4.0)
